tohil/__init__.py
tohil/_tohil.cpython-37m-arm-linux-gnueabihf.so
tohil-3.2.0.data/data/my_data/data_file
tohil-3.2.0.dist-info/METADATA
tohil-3.2.0.dist-info/WHEEL
tohil-3.2.0.dist-info/top_level.txt
tohil-3.2.0.dist-info/RECORD
